kicksaw_data_mapping_serializer/__init__.py
kicksaw_data_mapping_serializer/classes.py
kicksaw_data_mapping_serializer/main.py
kicksaw_data_mapping_serializer-0.1.0.dist-info/WHEEL
kicksaw_data_mapping_serializer-0.1.0.dist-info/METADATA
kicksaw_data_mapping_serializer-0.1.0.dist-info/RECORD
